latino/__init__.py
latino/client.py
latino/constants.py
latino/models.py
latino/urls.py
latino-0.1.1.dist-info/LICENSE
latino-0.1.1.dist-info/METADATA
latino-0.1.1.dist-info/WHEEL
latino-0.1.1.dist-info/top_level.txt
latino-0.1.1.dist-info/RECORD
