Metadata-Version: 2.1
Name: latino
Version: 0.1.1
Summary: Traduttore Latino: lemma, paradigma, grammatica e traduzione da Dizionario Olivetti ©.
Home-page: https://github.com/lindaniele/latino
Author: Daniele Lin
Author-email: lindaniele25@gmail.com
License: MIT
Keywords: latino,dizionario,olivetti,traduttore,latin,paradigma,traduzione,translator,translate,latinum,paradigm,grammar,api
Platform: UNKNOWN
Classifier: Programming Language :: Python :: 3.8
Classifier: License :: OSI Approved :: MIT License
Classifier: Operating System :: OS Independent
Requires-Python: >=3.8
License-File: LICENSE
Requires-Dist: lxml
Requires-Dist: bs4
Requires-Dist: requests
